LICENSE
README.md
setup.py
autobio_tool.egg-info/PKG-INFO
autobio_tool.egg-info/SOURCES.txt
autobio_tool.egg-info/dependency_links.txt
autobio_tool.egg-info/top_level.txt
autobiotool/__init__.py
autobiotool/autogluon_test.py
autobiotool/main_CB.py
autobiotool/main_KNN.py
autobiotool/main_MLP.py
autobiotool/main_RF.py
autobiotool/main_SVM.py
autobiotool/main_XGB.py
autobiotool/main_adaboost.py
autobiotool/main_auto.py
autobiotool/main_lightGBM.py
autobiotool/utils.py
autobiotool/Classifier/__init__.py
autobiotool/Classifier/Auto/AutoClassifier.py
autobiotool/Classifier/Auto/__init__.py
autobiotool/Classifier/Auto/utils.py
autobiotool/Classifier/Bayesian_Optimization/AdaBoostClassifier.py
autobiotool/Classifier/Bayesian_Optimization/AutoClassifier.py
autobiotool/Classifier/Bayesian_Optimization/CatBoostClassifier.py
autobiotool/Classifier/Bayesian_Optimization/KNeighborsClassifier.py
autobiotool/Classifier/Bayesian_Optimization/LightGBMClassifier.py
autobiotool/Classifier/Bayesian_Optimization/MLPClassifier.py
autobiotool/Classifier/Bayesian_Optimization/RandomForestClassifier.py
autobiotool/Classifier/Bayesian_Optimization/SVMClassifier.py
autobiotool/Classifier/Bayesian_Optimization/XGBClassifier.py
autobiotool/Classifier/Bayesian_Optimization/__init__.py
autobiotool/Classifier/Genetic_Algorithm/AdaBoostClassifier.py
autobiotool/Classifier/Genetic_Algorithm/CatBoostClassifier.py
autobiotool/Classifier/Genetic_Algorithm/KNeighborsClassifier.py
autobiotool/Classifier/Genetic_Algorithm/LightGBMClassifier.py
autobiotool/Classifier/Genetic_Algorithm/MLPClassifier.py
autobiotool/Classifier/Genetic_Algorithm/RandomForestClassifier.py
autobiotool/Classifier/Genetic_Algorithm/SVMClassifier.py
autobiotool/Classifier/Genetic_Algorithm/XGBClassifier.py
autobiotool/Classifier/Genetic_Algorithm/__init__.py
autobiotool/Classifier/Genetic_Algorithm/demo.py
autobiotool/LinkPrediction/Initialize.py
autobiotool/LinkPrediction/LinkPrediction.py
autobiotool/LinkPrediction/__init__.py
autobiotool/LinkPrediction/Evaluation_Indicators/AUC.py
autobiotool/LinkPrediction/Evaluation_Indicators/__init__.py
