Metadata-Version: 2.1
Name: autobio-tool
Version: 0.1.9
Summary: A tool for prediction of molecules associations
Home-page: https://github.com/haohaodaren/autobio-tool.git
Author: kaizheng&&haoyuanli
Author-email: a1242884508@gmail.com
License: UNKNOWN
Platform: UNKNOWN
Classifier: Programming Language :: Python :: 3
Classifier: License :: OSI Approved :: MIT License
Classifier: Operating System :: OS Independent
License-File: LICENSE
